zope/pagetemplate/__init__.py
zope/pagetemplate/engine.py
zope/pagetemplate/i18n.py
zope/pagetemplate/interfaces.py
zope/pagetemplate/pagetemplate.py
zope/pagetemplate/pagetemplatefile.py
zope/pagetemplate/tests/__init__.py
zope/pagetemplate/tests/batch.py
zope/pagetemplate/tests/test_basictemplate.py
zope/pagetemplate/tests/test_engine.py
zope/pagetemplate/tests/test_htmltests.py
zope/pagetemplate/tests/test_ptfile.py
zope/pagetemplate/tests/trusted.py
zope/pagetemplate/tests/util.py
zope/pagetemplate/tests/input/__init__.py
zope/pagetemplate/tests/input/checknotexpression.html
zope/pagetemplate/tests/input/checknothing.html
zope/pagetemplate/tests/input/checkpathalt.html
zope/pagetemplate/tests/input/checkpathnothing.html
zope/pagetemplate/tests/input/checkwithxmlheader.html
zope/pagetemplate/tests/input/dtml1.html
zope/pagetemplate/tests/input/dtml3.html
zope/pagetemplate/tests/input/globalsshadowlocals.html
zope/pagetemplate/tests/input/loop1.html
zope/pagetemplate/tests/input/recursive.html
zope/pagetemplate/tests/input/stringexpression.html
zope/pagetemplate/tests/input/teeshop1.html
zope/pagetemplate/tests/input/teeshop2.html
zope/pagetemplate/tests/input/teeshoplaf.html
zope/pagetemplate/tests/input/translation.html
zope/pagetemplate/tests/output/__init__.py
zope/pagetemplate/tests/output/checknotexpression.html
zope/pagetemplate/tests/output/checknothing.html
zope/pagetemplate/tests/output/checkpathalt.html
zope/pagetemplate/tests/output/checkpathnothing.html
zope/pagetemplate/tests/output/checkwithxmlheader.html
zope/pagetemplate/tests/output/dtml1a.html
zope/pagetemplate/tests/output/dtml1b.html
zope/pagetemplate/tests/output/dtml3.html
zope/pagetemplate/tests/output/globalsshadowlocals.html
zope/pagetemplate/tests/output/loop1.html
zope/pagetemplate/tests/output/recursive.html
zope/pagetemplate/tests/output/stringexpression.html
zope/pagetemplate/tests/output/teeshop1.html
zope/pagetemplate/tests/output/teeshop2.html
zope_pagetemplate-6.0.dist-info/licenses/LICENSE.txt
zope_pagetemplate-6.0.dist-info/METADATA
zope_pagetemplate-6.0.dist-info/WHEEL
zope_pagetemplate-6.0.dist-info/top_level.txt
zope_pagetemplate-6.0.dist-info/RECORD
