Metadata-Version: 2.4
Name: zope.pagetemplate
Version: 6.0
Summary: Zope Page Templates
Home-page: https://github.com/zopefoundation/zope.pagetemplate
Author: Zope Foundation and Contributors
Author-email: zope-dev@zope.dev
License: ZPL-2.1
Keywords: zope3 page template
Classifier: Development Status :: 5 - Production/Stable
Classifier: Environment :: Web Environment
Classifier: Intended Audience :: Developers
Classifier: License :: OSI Approved :: Zope Public License
Classifier: Programming Language :: Python
Classifier: Programming Language :: Python :: 3
Classifier: Programming Language :: Python :: 3.9
Classifier: Programming Language :: Python :: 3.10
Classifier: Programming Language :: Python :: 3.11
Classifier: Programming Language :: Python :: 3.12
Classifier: Programming Language :: Python :: 3.13
Classifier: Programming Language :: Python :: Implementation :: CPython
Classifier: Programming Language :: Python :: Implementation :: PyPy
Classifier: Natural Language :: English
Classifier: Operating System :: OS Independent
Classifier: Topic :: Internet :: WWW/HTTP
Classifier: Framework :: Zope :: 3
Requires-Python: >=3.9
License-File: LICENSE.txt
Requires-Dist: setuptools
Requires-Dist: zope.interface
Requires-Dist: zope.component
Requires-Dist: zope.tales
Requires-Dist: zope.tal>=4.2.0
Requires-Dist: zope.i18n>=4.0.1
Requires-Dist: zope.i18nmessageid
Requires-Dist: zope.traversing
Provides-Extra: test
Requires-Dist: zope.proxy; extra == "test"
Requires-Dist: zope.security; extra == "test"
Requires-Dist: zope.testing; extra == "test"
Requires-Dist: zope.testrunner>=6.4; extra == "test"
Requires-Dist: zope.untrustedpython>=5.0.dev0; extra == "test"
Provides-Extra: untrusted
Requires-Dist: zope.untrustedpython>=5.0.dev0; extra == "untrusted"
Provides-Extra: docs
Requires-Dist: Sphinx; extra == "docs"
Requires-Dist: repoze.sphinx.autointerface; extra == "docs"
Dynamic: author
Dynamic: author-email
Dynamic: classifier
Dynamic: description
Dynamic: home-page
Dynamic: keywords
Dynamic: license
Dynamic: license-file
Dynamic: provides-extra
Dynamic: requires-dist
Dynamic: requires-python
Dynamic: summary
